{
  "slices": {
    "components": {
      "flower": {
        "library": "slices",
        "id": "flower",
        "name": "Flower",
        "description": "Flower",
        "model": {
          "id": "flower",
          "type": "SharedSlice",
          "name": "Flower",
          "description": "Flower",
          "variations": [
            {
              "id": "default",
              "name": "Default",
              "docURL": "...",
              "version": "sktwi1xtmkfgx8626",
              "description": "Flower",
              "primary": {
                "title": {
                  "type": "StructuredText",
                  "config": {
                    "label": "Róslilja",
                    "placeholder": "",
                    "allowTargetBlank": true,
                    "single": "heading1"
                  }
                },
                "description": {
                  "type": "StructuredText",
                  "config": {
                    "label": "Róslilja er falleg ",
                    "placeholder": "",
                    "allowTargetBlank": true,
                    "single": "paragraph"
                  }
                }
              },
              "items": {},
              "imageUrl": "https://images.prismic.io/slice-machine/621a5ec4-0387-4bc5-9860-2dd46cbc07cd_default_ss.png?auto=compress,format"
            }
          ]
        },
        "mocks": {
          "default": {
            "variation": "default",
            "name": "Default",
            "slice_type": "flower",
            "items": [],
            "primary": {
              "title": [
                {
                  "type": "heading1",
                  "text": "Enhance next-generation web-readiness",
                  "spans": []
                }
              ],
              "description": [
                {
                  "type": "paragraph",
                  "text": "Incididunt quis cupidatat consequat non Lorem exercitation aliquip exercitation dolore ex enim laboris deserunt do in. Nulla irure id ex cillum voluptate eiusmod fugiat exercitation officia sit pariatur.",
                  "spans": []
                }
              ]
            }
          }
        },
        "meta": {
          "fileName": "index",
          "extension": "js"
        },
        "screenshotPaths": {}
      },
      "gulros": {
        "library": "slices",
        "id": "gulros",
        "name": "Gulros",
        "description": "Gulros",
        "model": {
          "id": "gulros",
          "type": "SharedSlice",
          "name": "Gulros",
          "description": "Gulros",
          "variations": [
            {
              "id": "default",
              "name": "Default",
              "docURL": "...",
              "version": "sktwi1xtmkfgx8626",
              "description": "Gulros",
              "primary": {
                "title": {
                  "type": "StructuredText",
                  "config": {
                    "label": "Gulrós",
                    "placeholder": "Bara gulrós og allt um gull",
                    "allowTargetBlank": true,
                    "single": "heading1"
                  }
                },
                "description": {
                  "type": "StructuredText",
                  "config": {
                    "single": "paragraph",
                    "label": "Description",
                    "placeholder": "A nice description of your feature"
                  }
                }
              },
              "items": {},
              "imageUrl": "https://images.prismic.io/slice-machine/621a5ec4-0387-4bc5-9860-2dd46cbc07cd_default_ss.png?auto=compress,format"
            }
          ]
        },
        "mocks": {
          "default": {
            "variation": "default",
            "name": "Default",
            "slice_type": "gulros",
            "items": [],
            "primary": {
              "title": [
                {
                  "type": "heading1",
                  "text": "Integrate vertical platforms",
                  "spans": []
                }
              ],
              "description": [
                {
                  "type": "paragraph",
                  "text": "Occaecat in fugiat aute ea irure fugiat magna consequat ea officia minim consectetur eu excepteur. Qui laboris id aute ad laborum duis aliquip culpa irure.",
                  "spans": []
                }
              ]
            }
          }
        },
        "meta": {
          "fileName": "index",
          "extension": "js"
        },
        "screenshotPaths": {
          "default": {
            "path": "C:\\haskoli\\vor2022\\vefforritunII\\vefv6\\.slicemachine\\assets\\slices\\Gulros\\default\\preview.png",
            "width": 800,
            "height": 83
          }
        }
      },
      "gulrot": {
        "library": "slices",
        "id": "gulrot",
        "name": "Gulrot",
        "description": "Gulrot",
        "model": {
          "id": "gulrot",
          "type": "SharedSlice",
          "name": "Gulrot",
          "description": "Gulrot",
          "variations": [
            {
              "id": "default",
              "name": "Default",
              "docURL": "...",
              "version": "sktwi1xtmkfgx8626",
              "description": "Gulrot",
              "primary": {
                "title": {
                  "type": "StructuredText",
                  "config": {
                    "label": "Gulrót er gott og best",
                    "placeholder": "allt um gulrót",
                    "allowTargetBlank": true,
                    "single": "heading1"
                  }
                },
                "description": {
                  "type": "StructuredText",
                  "config": {
                    "single": "paragraph",
                    "label": "Description",
                    "placeholder": "A nice description of your feature"
                  }
                }
              },
              "items": {},
              "imageUrl": "https://images.prismic.io/slice-machine/621a5ec4-0387-4bc5-9860-2dd46cbc07cd_default_ss.png?auto=compress,format"
            }
          ]
        },
        "mocks": {
          "default": {
            "variation": "default",
            "name": "Default",
            "slice_type": "gulrot",
            "items": [],
            "primary": {
              "title": [
                {
                  "type": "heading1",
                  "text": "Brand 24/365 communities",
                  "spans": []
                }
              ],
              "description": [
                {
                  "type": "paragraph",
                  "text": "Enim ex laboris dolor veniam exercitation irure veniam.",
                  "spans": []
                }
              ]
            }
          }
        },
        "meta": {
          "fileName": "index",
          "extension": "js"
        },
        "screenshotPaths": {
          "default": {
            "path": "C:\\haskoli\\vor2022\\vefforritunII\\vefv6\\.slicemachine\\assets\\slices\\Gulrot\\default\\preview.png",
            "width": 800,
            "height": 65
          }
        }
      },
      "ros": {
        "library": "slices",
        "id": "ros",
        "name": "Ros",
        "description": "Ros",
        "model": {
          "id": "ros",
          "type": "SharedSlice",
          "name": "Ros",
          "description": "Ros",
          "variations": [
            {
              "id": "default",
              "name": "Default",
              "docURL": "...",
              "version": "sktwi1xtmkfgx8626",
              "description": "Ros",
              "primary": {
                "title": {
                  "type": "StructuredText",
                  "config": {
                    "label": "Rós",
                    "placeholder": "Allt um rós ",
                    "allowTargetBlank": true,
                    "single": "heading1"
                  }
                },
                "description": {
                  "type": "StructuredText",
                  "config": {
                    "single": "paragraph",
                    "label": "Description",
                    "placeholder": "A nice description of your feature"
                  }
                }
              },
              "items": {},
              "imageUrl": "https://images.prismic.io/slice-machine/621a5ec4-0387-4bc5-9860-2dd46cbc07cd_default_ss.png?auto=compress,format"
            }
          ]
        },
        "mocks": {
          "default": {
            "variation": "default",
            "name": "Default",
            "slice_type": "ros",
            "items": [],
            "primary": {
              "title": [
                {
                  "type": "heading1",
                  "text": "Mesh best-of-breed mindshare",
                  "spans": []
                }
              ],
              "description": [
                {
                  "type": "paragraph",
                  "text": "Non fugiat ut dolor dolor in enim adipisicing aliqua aliquip aliqua laboris sunt commodo consectetur. Id ad eu nulla et laboris irure deserunt sunt. Officia sint adipisicing cupidatat elit exercitation labore non sunt quis exercitation ad.",
                  "spans": []
                }
              ]
            }
          }
        },
        "meta": {
          "fileName": "index",
          "extension": "js"
        },
        "screenshotPaths": {
          "default": {
            "path": "C:\\haskoli\\vor2022\\vefforritunII\\vefv6\\.slicemachine\\assets\\slices\\Ros\\default\\preview.png",
            "width": 800,
            "height": 65
          }
        }
      }
    }
  }
}