[
  {
    "variation": "default",
    "name": "Default",
    "slice_type": "hvitros",
    "items": [],
    "primary": {
      "title": [
        {
          "type": "heading1",
          "text": "Grow best-of-breed e-markets",
          "spans": []
        }
      ],
      "description": [
        {
          "type": "paragraph",
          "text": "Sit quis labore eiusmod dolor. Eiusmod enim dolore cillum.",
          "spans": []
        }
      ],
      "hvitrosImage": {
        "dimensions": {
          "width": 900,
          "height": 500
        },
        "alt": "Placeholder image",
        "copyright": null,
        "url": "https://images.unsplash.com/photo-1448932223592-d1fc686e76ea?w=900&h=500&fit=crop"
      }
    }
  }
]